decleverett/__init__.py
decleverett/base.py
decleverett/log.py
decleverett/yaml.py
decleverett-0.0.0.dist-info/METADATA
decleverett-0.0.0.dist-info/WHEEL
decleverett-0.0.0.dist-info/top_level.txt
decleverett-0.0.0.dist-info/RECORD
